<?xml version="1.0" encoding="UTF-8"?>
<reaction_data xmlns:xsi="http://www.w3.org/2001/XMLSchema-instance" xsi:schemaLocation="http://libnucnet.sourceforge.net/xsd_pub/2014-12-13/libnucnet__reac/ http://libnucnet.sourceforge.net/xsd_pub/2014-12-13/libnucnet__reac.xsd">
  <!--h1 + pt204 -> au205 + gamma-->
  <reaction>
    <source>rapp</source>
    <reactant>h1</reactant>
    <reactant>pt204</reactant>
    <product>au205</product>
    <product>gamma</product>
    <non_smoker_fit>
      <fit note="r">
        <spint>0</spint>
        <spinf>0</spinf>
        <TlowHf>0.01</TlowHf>
        <Tlowfit>0.01</Tlowfit>
        <Thighfit>10</Thighfit>
        <acc>0</acc>
        <a1>-3058.97</a1>
        <a2>61.5394</a2>
        <a3>-6008.94</a3>
        <a4>9475.26</a4>
        <a5>-532.198</a5>
        <a6>29.1078</a6>
        <a7>-4604.15</a7>
        <a8>0</a8>
      </fit>
    </non_smoker_fit>
  </reaction>
</reaction_data>
