<?xml version="1.0" encoding="UTF-8"?>
<reaction_data xmlns:xsi="http://www.w3.org/2001/XMLSchema-instance" xsi:schemaLocation="http://libnucnet.sourceforge.net/xsd_pub/2014-12-13/libnucnet__reac/ http://libnucnet.sourceforge.net/xsd_pub/2014-12-13/libnucnet__reac.xsd">
  <!--xe107 + gamma -> n + xe106-->
  <reaction>
    <source>rapp</source>
    <reactant>xe107</reactant>
    <reactant>gamma</reactant>
    <product>n</product>
    <product>xe106</product>
    <non_smoker_fit>
      <fit note="r">
        <spint>0</spint>
        <spinf>0</spinf>
        <TlowHf>0.01</TlowHf>
        <Tlowfit>0.01</Tlowfit>
        <Thighfit>10</Thighfit>
        <acc>0</acc>
        <a1>36.719</a1>
        <a2>-148.732</a2>
        <a3>-0.216097</a3>
        <a4>-2.47911</a4>
        <a5>0.671508</a5>
        <a6>-0.107876</a6>
        <a7>2.07649</a7>
        <a8>0</a8>
      </fit>
    </non_smoker_fit>
  </reaction>
</reaction_data>
