<?xml version="1.0" encoding="UTF-8"?>
<reaction_data xmlns:xsi="http://www.w3.org/2001/XMLSchema-instance" xsi:schemaLocation="http://libnucnet.sourceforge.net/xsd_pub/2014-12-13/libnucnet__reac/ http://libnucnet.sourceforge.net/xsd_pub/2014-12-13/libnucnet__reac.xsd">
  <!--he4 + i159 -> h1 + xe162-->
  <reaction>
    <source>rapp</source>
    <reactant>he4</reactant>
    <reactant>i159</reactant>
    <product>h1</product>
    <product>xe162</product>
    <non_smoker_fit>
      <fit note="r">
        <spint>0</spint>
        <spinf>0</spinf>
        <TlowHf>0.01</TlowHf>
        <Tlowfit>0.01</Tlowfit>
        <Thighfit>10</Thighfit>
        <acc>0</acc>
        <a1>-1704.62</a1>
        <a2>-30.6623</a2>
        <a3>-4079.48</a3>
        <a4>5985.39</a4>
        <a5>-313.01</a5>
        <a6>16.2003</a6>
        <a7>-3008.27</a7>
        <a8>0</a8>
      </fit>
    </non_smoker_fit>
  </reaction>
</reaction_data>
