<?xml version="1.0" encoding="UTF-8"?>
<reaction_data xmlns:xsi="http://www.w3.org/2001/XMLSchema-instance" xsi:schemaLocation="http://libnucnet.sourceforge.net/xsd_pub/2014-12-13/libnucnet__reac/ http://libnucnet.sourceforge.net/xsd_pub/2014-12-13/libnucnet__reac.xsd">
  <!--he4 + as59 -> n + br62-->
  <reaction>
    <source>rapp</source>
    <reactant>he4</reactant>
    <reactant>as59</reactant>
    <product>n</product>
    <product>br62</product>
    <non_smoker_fit>
      <fit note="r">
        <spint>0</spint>
        <spinf>0</spinf>
        <TlowHf>0.01</TlowHf>
        <Tlowfit>0.01</Tlowfit>
        <Thighfit>10</Thighfit>
        <acc>0</acc>
        <a1>16.0704</a1>
        <a2>-197.043</a2>
        <a3>-0.514502</a3>
        <a4>-5.03704</a4>
        <a5>0.81448</a5>
        <a6>-0.041186</a6>
        <a7>0.628151</a7>
        <a8>0</a8>
      </fit>
    </non_smoker_fit>
  </reaction>
</reaction_data>
