<?xml version="1.0" encoding="UTF-8"?>
<reaction_data xmlns:xsi="http://www.w3.org/2001/XMLSchema-instance" xsi:schemaLocation="http://libnucnet.sourceforge.net/xsd_pub/2014-12-13/libnucnet__reac/ http://libnucnet.sourceforge.net/xsd_pub/2014-12-13/libnucnet__reac.xsd">
  <!--re183 + gamma -> he4 + ta179-->
  <reaction>
    <source>rapp</source>
    <reactant>re183</reactant>
    <reactant>gamma</reactant>
    <product>he4</product>
    <product>ta179</product>
    <non_smoker_fit>
      <fit note="r">
        <spint>0</spint>
        <spinf>0</spinf>
        <TlowHf>0.01</TlowHf>
        <Tlowfit>0.01</Tlowfit>
        <Thighfit>10</Thighfit>
        <acc>0</acc>
        <a1>-517.606</a1>
        <a2>17.9004</a2>
        <a3>-2856.85</a3>
        <a4>3472.23</a4>
        <a5>-161.878</a5>
        <a6>7.54948</a6>
        <a7>-1888.04</a7>
        <a8>0</a8>
      </fit>
    </non_smoker_fit>
  </reaction>
</reaction_data>
