<?xml version="1.0" encoding="UTF-8"?>
<reaction_data xmlns:xsi="http://www.w3.org/2001/XMLSchema-instance" xsi:schemaLocation="http://libnucnet.sourceforge.net/xsd_pub/2014-12-13/libnucnet__reac/ http://libnucnet.sourceforge.net/xsd_pub/2014-12-13/libnucnet__reac.xsd">
  <!--si33 + gamma -> h1 + al32-->
  <reaction>
    <source>rapp</source>
    <reactant>si33</reactant>
    <reactant>gamma</reactant>
    <product>h1</product>
    <product>al32</product>
    <non_smoker_fit>
      <fit note="r">
        <spint>0</spint>
        <spinf>0</spinf>
        <TlowHf>0.01</TlowHf>
        <Tlowfit>0.01</Tlowfit>
        <Thighfit>10</Thighfit>
        <acc>0</acc>
        <a1>92.9156</a1>
        <a2>-197.279</a2>
        <a3>115.138</a3>
        <a4>-191.33</a4>
        <a5>10.1373</a5>
        <a6>-0.546421</a6>
        <a7>98.3591</a7>
        <a8>0</a8>
      </fit>
    </non_smoker_fit>
  </reaction>
</reaction_data>
