<?xml version="1.0" encoding="UTF-8"?>
<reaction_data xmlns:xsi="http://www.w3.org/2001/XMLSchema-instance" xsi:schemaLocation="http://libnucnet.sourceforge.net/xsd_pub/2014-12-13/libnucnet__reac/ http://libnucnet.sourceforge.net/xsd_pub/2014-12-13/libnucnet__reac.xsd">
  <!--n + er195 -> er196 + gamma-->
  <reaction>
    <source>rapp</source>
    <reactant>n</reactant>
    <reactant>er195</reactant>
    <product>er196</product>
    <product>gamma</product>
    <non_smoker_fit>
      <fit note="r">
        <spint>0</spint>
        <spinf>0</spinf>
        <TlowHf>0.01</TlowHf>
        <Tlowfit>0.01</Tlowfit>
        <Thighfit>10</Thighfit>
        <acc>0</acc>
        <a1>-26.5864</a1>
        <a2>0.172075</a2>
        <a3>-20.6642</a3>
        <a4>58.7068</a4>
        <a5>-4.38348</a5>
        <a6>0.0846824</a6>
        <a7>-21.7822</a7>
        <a8>0</a8>
      </fit>
    </non_smoker_fit>
  </reaction>
</reaction_data>
