<?xml version="1.0" encoding="UTF-8"?>
<reaction_data xmlns:xsi="http://www.w3.org/2001/XMLSchema-instance" xsi:schemaLocation="http://libnucnet.sourceforge.net/xsd_pub/2014-12-13/libnucnet__reac/ http://libnucnet.sourceforge.net/xsd_pub/2014-12-13/libnucnet__reac.xsd">
  <!--he4 + hf237 -> h1 + ta240-->
  <reaction>
    <source>rapp</source>
    <reactant>he4</reactant>
    <reactant>hf237</reactant>
    <product>h1</product>
    <product>ta240</product>
    <non_smoker_fit>
      <fit note="r">
        <spint>0</spint>
        <spinf>0</spinf>
        <TlowHf>0.01</TlowHf>
        <Tlowfit>0.01</Tlowfit>
        <Thighfit>10</Thighfit>
        <acc>0</acc>
        <a1>-609.43</a1>
        <a2>-76.4077</a2>
        <a3>-4295.9</a3>
        <a4>4996.11</a4>
        <a5>-209.818</a5>
        <a6>8.95556</a6>
        <a7>-2819.84</a7>
        <a8>0</a8>
      </fit>
    </non_smoker_fit>
  </reaction>
</reaction_data>
