<?xml version="1.0" encoding="UTF-8"?>
<reaction_data xmlns:xsi="http://www.w3.org/2001/XMLSchema-instance" xsi:schemaLocation="http://libnucnet.sourceforge.net/xsd_pub/2014-12-13/libnucnet__reac/ http://libnucnet.sourceforge.net/xsd_pub/2014-12-13/libnucnet__reac.xsd">
  <!--h1 + ca67 -> sc68 + gamma-->
  <reaction>
    <source>rapp</source>
    <reactant>h1</reactant>
    <reactant>ca67</reactant>
    <product>sc68</product>
    <product>gamma</product>
    <non_smoker_fit>
      <fit note="r">
        <spint>0</spint>
        <spinf>0</spinf>
        <TlowHf>0.01</TlowHf>
        <Tlowfit>0.01</Tlowfit>
        <Thighfit>10</Thighfit>
        <acc>0</acc>
        <a1>124.737</a1>
        <a2>-6.17302</a2>
        <a3>235.165</a3>
        <a4>-380.92</a4>
        <a5>21.3428</a5>
        <a6>-1.20926</a6>
        <a7>189.508</a7>
        <a8>0</a8>
      </fit>
    </non_smoker_fit>
  </reaction>
</reaction_data>
