<?xml version="1.0" encoding="UTF-8"?>
<reaction_data xmlns:xsi="http://www.w3.org/2001/XMLSchema-instance" xsi:schemaLocation="http://libnucnet.sourceforge.net/xsd_pub/2014-12-13/libnucnet__reac/ http://libnucnet.sourceforge.net/xsd_pub/2014-12-13/libnucnet__reac.xsd">
  <!--he4 + nd136 -> h1 + pm139-->
  <reaction>
    <source>rapp</source>
    <reactant>he4</reactant>
    <reactant>nd136</reactant>
    <product>h1</product>
    <product>pm139</product>
    <non_smoker_fit>
      <fit note="r">
        <spint>0</spint>
        <spinf>0</spinf>
        <TlowHf>0.01</TlowHf>
        <Tlowfit>0.01</Tlowfit>
        <Thighfit>10</Thighfit>
        <acc>0</acc>
        <a1>-1995.98</a1>
        <a2>-44.6446</a2>
        <a3>-3360.39</a3>
        <a4>5608.58</a4>
        <a5>-331.064</a5>
        <a6>18.9258</a6>
        <a7>-2643.17</a7>
        <a8>0</a8>
      </fit>
    </non_smoker_fit>
  </reaction>
</reaction_data>
