<?xml version="1.0" encoding="UTF-8"?>
<reaction_data xmlns:xsi="http://www.w3.org/2001/XMLSchema-instance" xsi:schemaLocation="http://libnucnet.sourceforge.net/xsd_pub/2014-12-13/libnucnet__reac/ http://libnucnet.sourceforge.net/xsd_pub/2014-12-13/libnucnet__reac.xsd">
  <!--n + se68 -> se69 + gamma-->
  <reaction>
    <source>rapp</source>
    <reactant>n</reactant>
    <reactant>se68</reactant>
    <product>se69</product>
    <product>gamma</product>
    <non_smoker_fit>
      <fit note="r">
        <spint>0</spint>
        <spinf>0</spinf>
        <TlowHf>0.01</TlowHf>
        <Tlowfit>0.01</Tlowfit>
        <Thighfit>10</Thighfit>
        <acc>0</acc>
        <a1>14.6475</a1>
        <a2>0.021815</a2>
        <a3>-1.12292</a3>
        <a4>-0.506862</a4>
        <a5>0.676388</a5>
        <a6>-0.113857</a6>
        <a7>-0.329642</a7>
        <a8>0</a8>
      </fit>
    </non_smoker_fit>
  </reaction>
</reaction_data>
