<?xml version="1.0" encoding="UTF-8"?>
<reaction_data xmlns:xsi="http://www.w3.org/2001/XMLSchema-instance" xsi:schemaLocation="http://libnucnet.sourceforge.net/xsd_pub/2014-12-13/libnucnet__reac/ http://libnucnet.sourceforge.net/xsd_pub/2014-12-13/libnucnet__reac.xsd">
  <!--rb119 + gamma -> he4 + br115-->
  <reaction>
    <source>rapp</source>
    <reactant>rb119</reactant>
    <reactant>gamma</reactant>
    <product>he4</product>
    <product>br115</product>
    <non_smoker_fit>
      <fit note="r">
        <spint>0</spint>
        <spinf>0</spinf>
        <TlowHf>0.01</TlowHf>
        <Tlowfit>0.01</Tlowfit>
        <Thighfit>10</Thighfit>
        <acc>0</acc>
        <a1>-814.847</a1>
        <a2>-211.299</a2>
        <a3>-3276.09</a3>
        <a4>4226.02</a4>
        <a5>-205.664</a5>
        <a6>10.0504</a6>
        <a7>-2239.43</a7>
        <a8>0</a8>
      </fit>
    </non_smoker_fit>
  </reaction>
</reaction_data>
