<?xml version="1.0" encoding="UTF-8"?>
<reaction_data xmlns:xsi="http://www.w3.org/2001/XMLSchema-instance" xsi:schemaLocation="http://libnucnet.sourceforge.net/xsd_pub/2014-12-13/libnucnet__reac/ http://libnucnet.sourceforge.net/xsd_pub/2014-12-13/libnucnet__reac.xsd">
  <!--he4 + ti57 -> n + cr60-->
  <reaction>
    <source>rapp</source>
    <reactant>he4</reactant>
    <reactant>ti57</reactant>
    <product>n</product>
    <product>cr60</product>
    <non_smoker_fit>
      <fit note="r">
        <spint>0</spint>
        <spinf>0</spinf>
        <TlowHf>0.01</TlowHf>
        <Tlowfit>0.01</Tlowfit>
        <Thighfit>10</Thighfit>
        <acc>0</acc>
        <a1>-1049.69</a1>
        <a2>16.7534</a2>
        <a3>-1818.24</a3>
        <a4>2996.03</a4>
        <a5>-179.173</a5>
        <a6>10.2882</a6>
        <a7>-1404.54</a7>
        <a8>0</a8>
      </fit>
    </non_smoker_fit>
  </reaction>
</reaction_data>
