<?xml version="1.0" encoding="UTF-8"?>
<reaction_data xmlns:xsi="http://www.w3.org/2001/XMLSchema-instance" xsi:schemaLocation="http://libnucnet.sourceforge.net/xsd_pub/2014-12-13/libnucnet__reac/ http://libnucnet.sourceforge.net/xsd_pub/2014-12-13/libnucnet__reac.xsd">
  <!--ag96 + gamma -> n + ag95-->
  <reaction>
    <source>rapp</source>
    <reactant>ag96</reactant>
    <reactant>gamma</reactant>
    <product>n</product>
    <product>ag95</product>
    <non_smoker_fit>
      <fit note="r">
        <spint>0</spint>
        <spinf>0</spinf>
        <TlowHf>0.01</TlowHf>
        <Tlowfit>0.01</Tlowfit>
        <Thighfit>10</Thighfit>
        <acc>0</acc>
        <a1>47.4955</a1>
        <a2>-147.193</a2>
        <a3>2.86858</a3>
        <a4>-11.7304</a4>
        <a5>1.14297</a5>
        <a6>-0.126391</a6>
        <a7>5.77327</a7>
        <a8>0</a8>
      </fit>
    </non_smoker_fit>
  </reaction>
</reaction_data>
