<?xml version="1.0" encoding="UTF-8"?>
<reaction_data xmlns:xsi="http://www.w3.org/2001/XMLSchema-instance" xsi:schemaLocation="http://libnucnet.sourceforge.net/xsd_pub/2014-12-13/libnucnet__reac/ http://libnucnet.sourceforge.net/xsd_pub/2014-12-13/libnucnet__reac.xsd">
  <!--n + tc118 -> h1 + mo118-->
  <reaction>
    <source>rapp</source>
    <reactant>n</reactant>
    <reactant>tc118</reactant>
    <product>h1</product>
    <product>mo118</product>
    <non_smoker_fit>
      <fit note="r">
        <spint>0</spint>
        <spinf>0</spinf>
        <TlowHf>0.01</TlowHf>
        <Tlowfit>0.01</Tlowfit>
        <Thighfit>10</Thighfit>
        <acc>0</acc>
        <a1>241.68</a1>
        <a2>-125.442</a2>
        <a3>502.955</a3>
        <a4>-780.17</a4>
        <a5>42.8186</a5>
        <a6>-2.38828</a6>
        <a7>392.899</a7>
        <a8>0</a8>
      </fit>
    </non_smoker_fit>
  </reaction>
</reaction_data>
