<?xml version="1.0" encoding="UTF-8"?>
<reaction_data xmlns:xsi="http://www.w3.org/2001/XMLSchema-instance" xsi:schemaLocation="http://libnucnet.sourceforge.net/xsd_pub/2014-12-13/libnucnet__reac/ http://libnucnet.sourceforge.net/xsd_pub/2014-12-13/libnucnet__reac.xsd">
  <!--h1 + bi189 -> he4 + pb186-->
  <reaction>
    <source>rapp</source>
    <reactant>h1</reactant>
    <reactant>bi189</reactant>
    <product>he4</product>
    <product>pb186</product>
    <non_smoker_fit>
      <fit note="r">
        <spint>0</spint>
        <spinf>0</spinf>
        <TlowHf>0.01</TlowHf>
        <Tlowfit>0.01</Tlowfit>
        <Thighfit>10</Thighfit>
        <acc>0</acc>
        <a1>-2870.73</a1>
        <a2>59.6089</a2>
        <a3>-5830.01</a3>
        <a4>9086.52</a4>
        <a5>-507.483</a5>
        <a6>27.917</a6>
        <a7>-4436.96</a7>
        <a8>0</a8>
      </fit>
    </non_smoker_fit>
  </reaction>
</reaction_data>
