<?xml version="1.0" encoding="UTF-8"?>
<reaction_data xmlns:xsi="http://www.w3.org/2001/XMLSchema-instance" xsi:schemaLocation="http://libnucnet.sourceforge.net/xsd_pub/2014-12-13/libnucnet__reac/ http://libnucnet.sourceforge.net/xsd_pub/2014-12-13/libnucnet__reac.xsd">
  <!--os235 + gamma -> he4 + w231-->
  <reaction>
    <source>rapp</source>
    <reactant>os235</reactant>
    <reactant>gamma</reactant>
    <product>he4</product>
    <product>w231</product>
    <non_smoker_fit>
      <fit note="r">
        <spint>0</spint>
        <spinf>0</spinf>
        <TlowHf>0.01</TlowHf>
        <Tlowfit>0.01</Tlowfit>
        <Thighfit>10</Thighfit>
        <acc>0</acc>
        <a1>336.846</a1>
        <a2>-60.4877</a2>
        <a3>-2699.64</a3>
        <a4>2340.45</a4>
        <a5>-86.0156</a5>
        <a6>3.22134</a6>
        <a7>-1481.55</a7>
        <a8>0</a8>
      </fit>
    </non_smoker_fit>
  </reaction>
</reaction_data>
