<?xml version="1.0" encoding="UTF-8"?>
<reaction_data xmlns:xsi="http://www.w3.org/2001/XMLSchema-instance" xsi:schemaLocation="http://libnucnet.sourceforge.net/xsd_pub/2014-12-13/libnucnet__reac/ http://libnucnet.sourceforge.net/xsd_pub/2014-12-13/libnucnet__reac.xsd">
  <!--n + zr113 -> h1 + y113-->
  <reaction>
    <source>rapp</source>
    <reactant>n</reactant>
    <reactant>zr113</reactant>
    <product>h1</product>
    <product>y113</product>
    <non_smoker_fit>
      <fit note="r">
        <spint>0</spint>
        <spinf>0</spinf>
        <TlowHf>0.01</TlowHf>
        <Tlowfit>0.01</Tlowfit>
        <Thighfit>10</Thighfit>
        <acc>0</acc>
        <a1>235.184</a1>
        <a2>-181.63</a2>
        <a3>471.582</a3>
        <a4>-739.253</a4>
        <a5>40.941</a5>
        <a6>-2.29325</a6>
        <a7>370.151</a7>
        <a8>0</a8>
      </fit>
    </non_smoker_fit>
  </reaction>
</reaction_data>
