<?xml version="1.0" encoding="UTF-8"?>
<reaction_data xmlns:xsi="http://www.w3.org/2001/XMLSchema-instance" xsi:schemaLocation="http://libnucnet.sourceforge.net/xsd_pub/2014-12-13/libnucnet__reac/ http://libnucnet.sourceforge.net/xsd_pub/2014-12-13/libnucnet__reac.xsd">
  <!--n + ga102 -> ga103 + gamma-->
  <reaction>
    <source>rapp</source>
    <reactant>n</reactant>
    <reactant>ga102</reactant>
    <product>ga103</product>
    <product>gamma</product>
    <non_smoker_fit>
      <fit note="r">
        <spint>0</spint>
        <spinf>0</spinf>
        <TlowHf>0.01</TlowHf>
        <Tlowfit>0.01</Tlowfit>
        <Thighfit>10</Thighfit>
        <acc>0</acc>
        <a1>-82.8188</a1>
        <a2>0.369349</a2>
        <a3>-48.5006</a3>
        <a4>139.955</a4>
        <a5>-9.70589</a5>
        <a6>0.494898</a6>
        <a7>-52.7128</a7>
        <a8>0</a8>
      </fit>
    </non_smoker_fit>
  </reaction>
</reaction_data>
