<?xml version="1.0" encoding="UTF-8"?>
<reaction_data xmlns:xsi="http://www.w3.org/2001/XMLSchema-instance" xsi:schemaLocation="http://libnucnet.sourceforge.net/xsd_pub/2014-12-13/libnucnet__reac/ http://libnucnet.sourceforge.net/xsd_pub/2014-12-13/libnucnet__reac.xsd">
  <!--he4 + la132 -> h1 + ce135-->
  <reaction>
    <source>rapp</source>
    <reactant>he4</reactant>
    <reactant>la132</reactant>
    <product>h1</product>
    <product>ce135</product>
    <non_smoker_fit>
      <fit note="r">
        <spint>0</spint>
        <spinf>0</spinf>
        <TlowHf>0.01</TlowHf>
        <Tlowfit>0.01</Tlowfit>
        <Thighfit>10</Thighfit>
        <acc>0</acc>
        <a1>-1644.04</a1>
        <a2>-7.99183</a2>
        <a3>-3703.52</a3>
        <a4>5563.66</a4>
        <a5>-302.58</a5>
        <a6>16.3262</a6>
        <a7>-2758.45</a7>
        <a8>0</a8>
      </fit>
    </non_smoker_fit>
  </reaction>
</reaction_data>
