<?xml version="1.0" encoding="UTF-8"?>
<reaction_data xmlns:xsi="http://www.w3.org/2001/XMLSchema-instance" xsi:schemaLocation="http://libnucnet.sourceforge.net/xsd_pub/2014-12-13/libnucnet__reac/ http://libnucnet.sourceforge.net/xsd_pub/2014-12-13/libnucnet__reac.xsd">
  <!--n + sr109 -> sr110 + gamma-->
  <reaction>
    <source>rapp</source>
    <reactant>n</reactant>
    <reactant>sr109</reactant>
    <product>sr110</product>
    <product>gamma</product>
    <non_smoker_fit>
      <fit note="r">
        <spint>0</spint>
        <spinf>0</spinf>
        <TlowHf>0.01</TlowHf>
        <Tlowfit>0.01</Tlowfit>
        <Thighfit>10</Thighfit>
        <acc>0</acc>
        <a1>27.7952</a1>
        <a2>0.0194311</a2>
        <a3>1.76173</a3>
        <a4>-20.981</a4>
        <a5>2.49527</a5>
        <a6>-0.299598</a6>
        <a7>4.8269</a7>
        <a8>0</a8>
      </fit>
    </non_smoker_fit>
  </reaction>
</reaction_data>
