<?xml version="1.0" encoding="UTF-8"?>
<reaction_data xmlns:xsi="http://www.w3.org/2001/XMLSchema-instance" xsi:schemaLocation="http://libnucnet.sourceforge.net/xsd_pub/2014-12-13/libnucnet__reac/ http://libnucnet.sourceforge.net/xsd_pub/2014-12-13/libnucnet__reac.xsd">
  <!--n + au237 -> au238 + gamma-->
  <reaction>
    <source>rapp</source>
    <reactant>n</reactant>
    <reactant>au237</reactant>
    <product>au238</product>
    <product>gamma</product>
    <non_smoker_fit>
      <fit note="r">
        <spint>0</spint>
        <spinf>0</spinf>
        <TlowHf>0.01</TlowHf>
        <Tlowfit>0.01</Tlowfit>
        <Thighfit>10</Thighfit>
        <acc>0</acc>
        <a1>-65.0885</a1>
        <a2>0.520741</a2>
        <a3>-56.4405</a3>
        <a4>136.235</a4>
        <a5>-9.35369</a5>
        <a6>0.307495</a6>
        <a7>-55.0157</a7>
        <a8>0</a8>
      </fit>
    </non_smoker_fit>
  </reaction>
</reaction_data>
